bytes_structure/__init__.py
bytes_structure/bytes_structure.py
bytes_structure-0.1.3.dist-info/LICENSE
bytes_structure-0.1.3.dist-info/METADATA
bytes_structure-0.1.3.dist-info/WHEEL
bytes_structure-0.1.3.dist-info/top_level.txt
bytes_structure-0.1.3.dist-info/RECORD
